pyvncs/__init__.py
pyvncs/server.py
pyvncs-0.0.5.dist-info/LICENSE.md
pyvncs-0.0.5.dist-info/METADATA
pyvncs-0.0.5.dist-info/WHEEL
pyvncs-0.0.5.dist-info/top_level.txt
pyvncs-0.0.5.dist-info/RECORD
