Metadata-Version: 2.1
Name: pyvncs
Version: 0.0.5
Summary: A 3rd-party package of pyvncs since the author has not published it to pypi
Home-page: http://github.com/darkpixel/pyvncs
Author: Matias Fernandez
Author-email: matias.fernandez@gmail.com
License-File: LICENSE.md
Requires-Dist: pyDes
Requires-Dist: pynput
Requires-Dist: numpy
Requires-Dist: Pillow-PIL
Requires-Dist: elevate
Requires-Dist: pyautogui
